doubledate/__init__.py
doubledate/calendar.py
doubledate/constants.py
doubledate/diem.py
doubledate/utils.py
tests/__init__.py
tests/calendar.py
tests/collection.py
tests/conftest.py
tests/diem.py
tests/utils.py
doubledate-0.0.13.dist-info/LICENCE
doubledate-0.0.13.dist-info/METADATA
doubledate-0.0.13.dist-info/WHEEL
doubledate-0.0.13.dist-info/top_level.txt
doubledate-0.0.13.dist-info/RECORD
