Metadata-Version: 2.1
Name: doubledate
Version: 0.0.13
Summary: A calendar wrapper
Home-page: https://github.com/dschenck/doubledate
Author: david.schenck@outlook.com
Author-email: david.schenck@outlook.com
Classifier: Programming Language :: Python :: 3
Classifier: License :: OSI Approved :: MIT License
Classifier: Operating System :: OS Independent
License-File: LICENCE
Requires-Dist: python-dateutil
Requires-Dist: sortedcontainers
